Metadata-Version: 2.4
Name: protgraph
Version: 0.3.12
Summary: ProtGraph, a graph generator for proteins.
Home-page: https://github.com/mpc-bioinformatics/ProtGraph
Author: Dominik Lux
License: BSD
Project-URL: Bugs, https://github.com/mpc-bioinformatics/ProtGraph/issues
Project-URL: Publication, https://doi.org/10.1093/bib/bbae671
Project-URL: ProGFASTAGen, https://github.com/mpc-bioinformatics/ProGFASTAGen
Classifier: Programming Language :: Python :: 3
Classifier: License :: OSI Approved :: BSD License
Requires-Python: >=3.9
License-File: LICENSE
Requires-Dist: networkx>=3.2.1
Requires-Dist: numpy>=2.0.2
Requires-Dist: igraph>=1.0.0
Requires-Dist: texttable>=1.6.4
Requires-Dist: tqdm>=4.64.1
Requires-Dist: biopython==1.85
Provides-Extra: postgres
Requires-Dist: psycopg>=3.0; extra == "postgres"
Provides-Extra: mysql
Requires-Dist: mysql; extra == "mysql"
Provides-Extra: sqlite
Requires-Dist: apsw>=3.42.0.0; extra == "sqlite"
Provides-Extra: cassandra
Requires-Dist: cassandra-driver; extra == "cassandra"
Provides-Extra: gremlin
Requires-Dist: gremlinpython; extra == "gremlin"
Provides-Extra: redis
Requires-Dist: redis; extra == "redis"
Requires-Dist: redisgraph; extra == "redis"
Provides-Extra: full
Requires-Dist: mysql; extra == "full"
Requires-Dist: psycopg>=3.0; extra == "full"
Requires-Dist: apsw>=3.42.0.0; extra == "full"
Requires-Dist: cassandra-driver; extra == "full"
Requires-Dist: redis; extra == "full"
Requires-Dist: redisgraph; extra == "full"
Requires-Dist: gremlinpython; extra == "full"
Dynamic: author
Dynamic: classifier
Dynamic: description
Dynamic: description-content-type
Dynamic: home-page
Dynamic: license
Dynamic: license-file
Dynamic: project-url
Dynamic: provides-extra
Dynamic: requires-dist
Dynamic: requires-python
Dynamic: summary
